{
  "obituaries": {
    "obituaries": {
      "url": "https://www.aderholdfuneralhome.com/obituaries",
      "funeral_home": "Aderholdfuneralhome",
      "scraped_at": "2025-07-25T23:43:57.265950",
      "name": "Obituaries",
      "summary": "Most Recent Obituaries | Aderhold Funeral Home\r\n  \n\n \n \n \n\n\n\n\n\n\n\n\n\n\n\n\n\n\n          \n\n\n       ABOUT US\n\n\n   About Us\n\n\n\n  Our Staff\n\n\n\n  Our Facilities\n\n\n\n  Testimonials\n\n\n\n  Why Choose Us\n\n\n\n  Contact Us\n\n\n\n\n\n  OBITUARIES\n\n\n   Obituary Listing\n\n\n\n  Send Flowers\n\n\n\n  Obituary Notifications\n\n\n\n  Live Services\n\n\n\n\n\n  SERVICES\n\n\n   Immediate Need\n\n\n\n  Services Overview\n\n\n\n  Traditional Services\n\n\n\n  Cremation Services\n\n\n\n  Personalization\n\n\n\n  Veteran Services\n\n\n\n  Monuments\n\n\n\n\n\n  PLANNING AHEAD\n\n\n ..."
    }
  },
  "last_updated": "2025-07-25T23:46:01.840702"
}